{
    "BaseTemperature": 9.5,
    "InitialSurfaceTemperature": 10,
    
    "DensityAir": [1.25, "kg/m3"],
    "SpecificHeatCapacityAir": [1005, "J/(kg*K)", "at 300 K"],
    
    "DensityHumus": [1300, "kg/m3"],
    "SpecificHeatCapacityHumus": [1920, "J/(kg*K)"],
    
    "DensityWater": [1000, "kg/m3"],
    "SpecificHeatCapacityWater": [4192, "J/(kg*K)"],
    
    "QuartzRawDensity": [2650, "kg/m3"],
    "SpecificHeatCapacityQuartz": [750, "J/(kg*K)"],
    
    "NTau": 0.65,
    "SoilAlbedo": 0.7,
    "SoilMoisture": 0.25,
    
    "type": "SoilTemperatureModuleParameters"
}